colorain/__init__.py
colorain/colorain.py
colorain/colours.py
colorain/console_game_engine.py
colorain/engine.py
colorain/errors.py
colorain/snake.py
colorain-0.0.52.dist-info/LICENSE
colorain-0.0.52.dist-info/METADATA
colorain-0.0.52.dist-info/WHEEL
colorain-0.0.52.dist-info/top_level.txt
colorain-0.0.52.dist-info/RECORD
