Metadata-Version: 2.1
Name: colorain
Version: 0.0.52
Summary: A simple styling package for making console programmes great again.
Home-page: https://github.com/susmit31/colorain
Author: Susmit Islam
Author-email: <susmitislam31@gmail.com>
License: UNKNOWN
Keywords: colour,color,terminal
Platform: UNKNOWN
